drf_base64/__init__.py
drf_base64/fields.py
drf_base64_filename-1.0.10.dist-info/LICENSE
drf_base64_filename-1.0.10.dist-info/METADATA
drf_base64_filename-1.0.10.dist-info/WHEEL
drf_base64_filename-1.0.10.dist-info/top_level.txt
drf_base64_filename-1.0.10.dist-info/RECORD
