Metadata-Version: 2.1
Name: drf-base64-filename
Version: 1.0.10
Summary: drf-base64-filename provides Serializer fields for using base64-encoded files with file names.
Author-email: lhy <dev@lhy.kr>
License: MIT License        
Project-URL: GitHub, https://github.com/LeeHanYeong/drf-base64-filename
Classifier: Framework :: Django
Classifier: Framework :: Django :: 3.2
Classifier: Programming Language :: Python
Requires-Python: >=3.9
License-File: LICENSE
Requires-Dist: drf-extra-fields
